setup.py
chromote/__init__.py
chromote.egg-info/PKG-INFO
chromote.egg-info/SOURCES.txt
chromote.egg-info/dependency_links.txt
chromote.egg-info/requires.txt
chromote.egg-info/top_level.txt