Metadata-Version: 1.0
Name: chromote
Version: 0.4.0
Summary: Python Wrapper for the Google Chrome Remote Debugging Protocol
Home-page: UNKNOWN
Author: Chris Seymour
Author-email: UNKNOWN
License: UNKNOWN
Platform: UNKNOWN
